ykutil/__init__.py
ykutil/accelerate_tools.py
ykutil/configuration.py
ykutil/constants.py
ykutil/data_model.py
ykutil/dataset.py
ykutil/evaluation.py
ykutil/executable.py
ykutil/function_api.py
ykutil/json_util.py
ykutil/llm_api.py
ykutil/log_util.py
ykutil/model.py
ykutil/multiproc.py
ykutil/openai_api.py
ykutil/os_tools.py
ykutil/pandas_util.py
ykutil/pandera_util.py
ykutil/peft_util.py
ykutil/plotting.py
ykutil/print_tools.py
ykutil/python.py
ykutil/sql.py
ykutil/statistics.py
ykutil/statistics_scipy.py
ykutil/tools.py
ykutil/torch_helpers.py
ykutil/training.py
ykutil/transformer.py
ykutil/types_util.py
ykutil/yaml_util.py
ykutil-0.0.18.dist-info/METADATA
ykutil-0.0.18.dist-info/WHEEL
ykutil-0.0.18.dist-info/entry_points.txt
ykutil-0.0.18.dist-info/RECORD
