Metadata-Version: 2.4
Name: ykutil
Version: 0.0.18
Summary: A continuously updates repository of utility functions.
Author-email: Yannik Keller <yannik@kelnet.de>
License: MIT License
Keywords: util
Requires-Python: >=3.10
Requires-Dist: tqdm
Provides-Extra: all
Requires-Dist: accelerate; extra == 'all'
Requires-Dist: bitsandbytes; extra == 'all'
Requires-Dist: datasets; extra == 'all'
Requires-Dist: openai; extra == 'all'
Requires-Dist: pandera; extra == 'all'
Requires-Dist: peft; extra == 'all'
Requires-Dist: torch; extra == 'all'
Requires-Dist: transformer-heads; extra == 'all'
Requires-Dist: transformers; extra == 'all'
